<?xml version="1.0" encoding="UTF-8"?>
<w:numbering xmlns:w="http://schemas.openxmlformats.org/wordprocessingml/2006/main"><w:abstractNum w:abstractNumId="802044"><w:lvl><w:start w:val="1"/><w:numFmt w:val="decimal"/><w:suff w:val="tab"/><w:lvlText w:val="%1."/><w:rPr><w:color w:val="3370ff"/></w:rPr></w:lvl></w:abstractNum><w:abstractNum w:abstractNumId="802045"><w:lvl><w:start w:val="1"/><w:numFmt w:val="lowerLetter"/><w:suff w:val="tab"/><w:lvlText w:val="%1."/><w:rPr><w:color w:val="3370ff"/></w:rPr></w:lvl></w:abstractNum><w:abstractNum w:abstractNumId="802046"><w:lvl><w:start w:val="2"/><w:numFmt w:val="lowerLetter"/><w:suff w:val="tab"/><w:lvlText w:val="%1."/><w:rPr><w:color w:val="3370ff"/></w:rPr></w:lvl></w:abstractNum><w:abstractNum w:abstractNumId="802047"><w:lvl><w:start w:val="3"/><w:numFmt w:val="lowerLetter"/><w:suff w:val="tab"/><w:lvlText w:val="%1."/><w:rPr><w:color w:val="3370ff"/></w:rPr></w:lvl></w:abstractNum><w:abstractNum w:abstractNumId="802048"><w:lvl><w:start w:val="2"/><w:numFmt w:val="decimal"/><w:suff w:val="tab"/><w:lvlText w:val="%1."/><w:rPr><w:color w:val="3370ff"/></w:rPr></w:lvl></w:abstractNum><w:abstractNum w:abstractNumId="802049"><w:lvl><w:numFmt w:val="bullet"/><w:suff w:val="tab"/><w:lvlText w:val="￮"/><w:rPr><w:color w:val="3370ff"/></w:rPr></w:lvl></w:abstractNum><w:abstractNum w:abstractNumId="802050"><w:lvl><w:numFmt w:val="bullet"/><w:suff w:val="tab"/><w:lvlText w:val="▪"/><w:rPr><w:color w:val="3370ff"/><w:sz w:val="11"/></w:rPr></w:lvl></w:abstractNum><w:abstractNum w:abstractNumId="802051"><w:lvl><w:numFmt w:val="bullet"/><w:suff w:val="tab"/><w:lvlText w:val="▪"/><w:rPr><w:color w:val="3370ff"/><w:sz w:val="11"/></w:rPr></w:lvl></w:abstractNum><w:abstractNum w:abstractNumId="802052"><w:lvl><w:numFmt w:val="bullet"/><w:suff w:val="tab"/><w:lvlText w:val="▪"/><w:rPr><w:color w:val="3370ff"/><w:sz w:val="11"/></w:rPr></w:lvl></w:abstractNum><w:abstractNum w:abstractNumId="802053"><w:lvl><w:numFmt w:val="bullet"/><w:suff w:val="tab"/><w:lvlText w:val="•"/><w:rPr><w:color w:val="3370ff"/></w:rPr></w:lvl></w:abstractNum><w:abstractNum w:abstractNumId="802054"><w:lvl><w:numFmt w:val="bullet"/><w:suff w:val="tab"/><w:lvlText w:val="•"/><w:rPr><w:color w:val="3370ff"/></w:rPr></w:lvl></w:abstractNum><w:abstractNum w:abstractNumId="802055"><w:lvl><w:numFmt w:val="bullet"/><w:suff w:val="tab"/><w:lvlText w:val="•"/><w:rPr><w:color w:val="3370ff"/></w:rPr></w:lvl></w:abstractNum><w:abstractNum w:abstractNumId="802056"><w:lvl><w:numFmt w:val="bullet"/><w:suff w:val="tab"/><w:lvlText w:val="•"/><w:rPr><w:color w:val="3370ff"/></w:rPr></w:lvl></w:abstractNum><w:abstractNum w:abstractNumId="802057"><w:lvl><w:numFmt w:val="bullet"/><w:suff w:val="tab"/><w:lvlText w:val="▪"/><w:rPr><w:color w:val="3370ff"/><w:sz w:val="11"/></w:rPr></w:lvl></w:abstractNum><w:abstractNum w:abstractNumId="802058"><w:lvl><w:numFmt w:val="bullet"/><w:suff w:val="tab"/><w:lvlText w:val="▪"/><w:rPr><w:color w:val="3370ff"/><w:sz w:val="11"/></w:rPr></w:lvl></w:abstractNum><w:abstractNum w:abstractNumId="802059"><w:lvl><w:numFmt w:val="bullet"/><w:suff w:val="tab"/><w:lvlText w:val="￮"/><w:rPr><w:color w:val="3370ff"/></w:rPr></w:lvl></w:abstractNum><w:abstractNum w:abstractNumId="802060"><w:lvl><w:numFmt w:val="bullet"/><w:suff w:val="tab"/><w:lvlText w:val="▪"/><w:rPr><w:color w:val="3370ff"/><w:sz w:val="11"/></w:rPr></w:lvl></w:abstractNum><w:abstractNum w:abstractNumId="802061"><w:lvl><w:numFmt w:val="bullet"/><w:suff w:val="tab"/><w:lvlText w:val="▪"/><w:rPr><w:color w:val="3370ff"/><w:sz w:val="11"/></w:rPr></w:lvl></w:abstractNum><w:abstractNum w:abstractNumId="802062"><w:lvl><w:numFmt w:val="bullet"/><w:suff w:val="tab"/><w:lvlText w:val="▪"/><w:rPr><w:color w:val="3370ff"/><w:sz w:val="11"/></w:rPr></w:lvl></w:abstractNum><w:abstractNum w:abstractNumId="802063"><w:lvl><w:start w:val="3"/><w:numFmt w:val="decimal"/><w:suff w:val="tab"/><w:lvlText w:val="%1."/><w:rPr><w:color w:val="3370ff"/></w:rPr></w:lvl></w:abstractNum><w:abstractNum w:abstractNumId="802064"><w:lvl><w:start w:val="4"/><w:numFmt w:val="decimal"/><w:suff w:val="tab"/><w:lvlText w:val="%1."/><w:rPr><w:color w:val="3370ff"/></w:rPr></w:lvl></w:abstractNum><w:abstractNum w:abstractNumId="802065"><w:lvl><w:start w:val="1"/><w:numFmt w:val="lowerLetter"/><w:suff w:val="tab"/><w:lvlText w:val="%1."/><w:rPr><w:color w:val="3370ff"/></w:rPr></w:lvl></w:abstractNum><w:abstractNum w:abstractNumId="802066"><w:lvl><w:start w:val="2"/><w:numFmt w:val="lowerLetter"/><w:suff w:val="tab"/><w:lvlText w:val="%1."/><w:rPr><w:color w:val="3370ff"/></w:rPr></w:lvl></w:abstractNum><w:abstractNum w:abstractNumId="802067"><w:lvl><w:start w:val="3"/><w:numFmt w:val="lowerLetter"/><w:suff w:val="tab"/><w:lvlText w:val="%1."/><w:rPr><w:color w:val="3370ff"/></w:rPr></w:lvl></w:abstractNum><w:abstractNum w:abstractNumId="802068"><w:lvl><w:start w:val="5"/><w:numFmt w:val="decimal"/><w:suff w:val="tab"/><w:lvlText w:val="%1."/><w:rPr><w:color w:val="3370ff"/></w:rPr></w:lvl></w:abstractNum><w:abstractNum w:abstractNumId="802069"><w:lvl><w:start w:val="6"/><w:numFmt w:val="decimal"/><w:suff w:val="tab"/><w:lvlText w:val="%1."/><w:rPr><w:color w:val="3370ff"/></w:rPr></w:lvl></w:abstractNum><w:abstractNum w:abstractNumId="802070"><w:lvl><w:start w:val="1"/><w:numFmt w:val="lowerLetter"/><w:suff w:val="tab"/><w:lvlText w:val="%1."/><w:rPr><w:color w:val="3370ff"/></w:rPr></w:lvl></w:abstractNum><w:abstractNum w:abstractNumId="802071"><w:lvl><w:start w:val="2"/><w:numFmt w:val="lowerLetter"/><w:suff w:val="tab"/><w:lvlText w:val="%1."/><w:rPr><w:color w:val="3370ff"/></w:rPr></w:lvl></w:abstractNum><w:abstractNum w:abstractNumId="802072"><w:lvl><w:start w:val="3"/><w:numFmt w:val="lowerLetter"/><w:suff w:val="tab"/><w:lvlText w:val="%1."/><w:rPr><w:color w:val="3370ff"/></w:rPr></w:lvl></w:abstractNum><w:abstractNum w:abstractNumId="802073"><w:lvl><w:start w:val="4"/><w:numFmt w:val="lowerLetter"/><w:suff w:val="tab"/><w:lvlText w:val="%1."/><w:rPr><w:color w:val="3370ff"/></w:rPr></w:lvl></w:abstractNum><w:abstractNum w:abstractNumId="802074"><w:lvl><w:start w:val="5"/><w:numFmt w:val="lowerLetter"/><w:suff w:val="tab"/><w:lvlText w:val="%1."/><w:rPr><w:color w:val="3370ff"/></w:rPr></w:lvl></w:abstractNum><w:abstractNum w:abstractNumId="802075"><w:lvl><w:start w:val="6"/><w:numFmt w:val="lowerLetter"/><w:suff w:val="tab"/><w:lvlText w:val="%1."/><w:rPr><w:color w:val="3370ff"/></w:rPr></w:lvl></w:abstractNum><w:abstractNum w:abstractNumId="802076"><w:lvl><w:start w:val="7"/><w:numFmt w:val="lowerLetter"/><w:suff w:val="tab"/><w:lvlText w:val="%1."/><w:rPr><w:color w:val="3370ff"/></w:rPr></w:lvl></w:abstractNum><w:abstractNum w:abstractNumId="802077"><w:lvl><w:start w:val="8"/><w:numFmt w:val="lowerLetter"/><w:suff w:val="tab"/><w:lvlText w:val="%1."/><w:rPr><w:color w:val="3370ff"/></w:rPr></w:lvl></w:abstractNum><w:abstractNum w:abstractNumId="802078"><w:lvl><w:start w:val="9"/><w:numFmt w:val="lowerLetter"/><w:suff w:val="tab"/><w:lvlText w:val="%1."/><w:rPr><w:color w:val="3370ff"/></w:rPr></w:lvl></w:abstractNum><w:abstractNum w:abstractNumId="802079"><w:lvl><w:start w:val="10"/><w:numFmt w:val="lowerLetter"/><w:suff w:val="tab"/><w:lvlText w:val="%1."/><w:rPr><w:color w:val="3370ff"/></w:rPr></w:lvl></w:abstractNum><w:abstractNum w:abstractNumId="802080"><w:lvl><w:start w:val="11"/><w:numFmt w:val="lowerLetter"/><w:suff w:val="tab"/><w:lvlText w:val="%1."/><w:rPr><w:color w:val="3370ff"/></w:rPr></w:lvl></w:abstractNum><w:abstractNum w:abstractNumId="802081"><w:lvl><w:start w:val="12"/><w:numFmt w:val="lowerLetter"/><w:suff w:val="tab"/><w:lvlText w:val="%1."/><w:rPr><w:color w:val="3370ff"/></w:rPr></w:lvl></w:abstractNum><w:abstractNum w:abstractNumId="802082"><w:lvl><w:start w:val="13"/><w:numFmt w:val="lowerLetter"/><w:suff w:val="tab"/><w:lvlText w:val="%1."/><w:rPr><w:color w:val="3370ff"/></w:rPr></w:lvl></w:abstractNum><w:abstractNum w:abstractNumId="802083"><w:lvl><w:start w:val="14"/><w:numFmt w:val="lowerLetter"/><w:suff w:val="tab"/><w:lvlText w:val="%1."/><w:rPr><w:color w:val="3370ff"/></w:rPr></w:lvl></w:abstractNum><w:abstractNum w:abstractNumId="802084"><w:lvl><w:start w:val="15"/><w:numFmt w:val="lowerLetter"/><w:suff w:val="tab"/><w:lvlText w:val="%1."/><w:rPr><w:color w:val="3370ff"/></w:rPr></w:lvl></w:abstractNum><w:abstractNum w:abstractNumId="802085"><w:lvl><w:start w:val="16"/><w:numFmt w:val="lowerLetter"/><w:suff w:val="tab"/><w:lvlText w:val="%1."/><w:rPr><w:color w:val="3370ff"/></w:rPr></w:lvl></w:abstractNum><w:abstractNum w:abstractNumId="802086"><w:lvl><w:start w:val="17"/><w:numFmt w:val="lowerLetter"/><w:suff w:val="tab"/><w:lvlText w:val="%1."/><w:rPr><w:color w:val="3370ff"/></w:rPr></w:lvl></w:abstractNum><w:abstractNum w:abstractNumId="802087"><w:lvl><w:start w:val="7"/><w:numFmt w:val="decimal"/><w:suff w:val="tab"/><w:lvlText w:val="%1."/><w:rPr><w:color w:val="3370ff"/></w:rPr></w:lvl></w:abstractNum><w:abstractNum w:abstractNumId="802088"><w:lvl><w:start w:val="8"/><w:numFmt w:val="decimal"/><w:suff w:val="tab"/><w:lvlText w:val="%1."/><w:rPr><w:color w:val="3370ff"/></w:rPr></w:lvl></w:abstractNum><w:abstractNum w:abstractNumId="802089"><w:lvl><w:start w:val="9"/><w:numFmt w:val="decimal"/><w:suff w:val="tab"/><w:lvlText w:val="%1."/><w:rPr><w:color w:val="3370ff"/></w:rPr></w:lvl></w:abstractNum><w:abstractNum w:abstractNumId="802090"><w:lvl><w:start w:val="1"/><w:numFmt w:val="decimal"/><w:suff w:val="tab"/><w:lvlText w:val="%1."/><w:rPr><w:color w:val="3370ff"/></w:rPr></w:lvl></w:abstractNum><w:abstractNum w:abstractNumId="802091"><w:lvl><w:start w:val="2"/><w:numFmt w:val="decimal"/><w:suff w:val="tab"/><w:lvlText w:val="%1."/><w:rPr><w:color w:val="3370ff"/></w:rPr></w:lvl></w:abstractNum><w:abstractNum w:abstractNumId="802092"><w:lvl><w:start w:val="3"/><w:numFmt w:val="decimal"/><w:suff w:val="tab"/><w:lvlText w:val="%1."/><w:rPr><w:color w:val="3370ff"/></w:rPr></w:lvl></w:abstractNum><w:abstractNum w:abstractNumId="802093"><w:lvl><w:start w:val="4"/><w:numFmt w:val="decimal"/><w:suff w:val="tab"/><w:lvlText w:val="%1."/><w:rPr><w:color w:val="3370ff"/></w:rPr></w:lvl></w:abstractNum><w:abstractNum w:abstractNumId="802094"><w:lvl><w:start w:val="5"/><w:numFmt w:val="decimal"/><w:suff w:val="tab"/><w:lvlText w:val="%1."/><w:rPr><w:color w:val="3370ff"/></w:rPr></w:lvl></w:abstractNum><w:abstractNum w:abstractNumId="802095"><w:lvl><w:start w:val="6"/><w:numFmt w:val="decimal"/><w:suff w:val="tab"/><w:lvlText w:val="%1."/><w:rPr><w:color w:val="3370ff"/></w:rPr></w:lvl></w:abstractNum><w:abstractNum w:abstractNumId="802096"><w:lvl><w:start w:val="7"/><w:numFmt w:val="decimal"/><w:suff w:val="tab"/><w:lvlText w:val="%1."/><w:rPr><w:color w:val="3370ff"/></w:rPr></w:lvl></w:abstractNum><w:num w:numId="1"><w:abstractNumId w:val="802044"/></w:num><w:num w:numId="2"><w:abstractNumId w:val="802045"/></w:num><w:num w:numId="3"><w:abstractNumId w:val="802046"/></w:num><w:num w:numId="4"><w:abstractNumId w:val="802047"/></w:num><w:num w:numId="5"><w:abstractNumId w:val="802048"/></w:num><w:num w:numId="6"><w:abstractNumId w:val="802049"/></w:num><w:num w:numId="7"><w:abstractNumId w:val="802050"/></w:num><w:num w:numId="8"><w:abstractNumId w:val="802051"/></w:num><w:num w:numId="9"><w:abstractNumId w:val="802052"/></w:num><w:num w:numId="10"><w:abstractNumId w:val="802053"/></w:num><w:num w:numId="11"><w:abstractNumId w:val="802054"/></w:num><w:num w:numId="12"><w:abstractNumId w:val="802055"/></w:num><w:num w:numId="13"><w:abstractNumId w:val="802056"/></w:num><w:num w:numId="14"><w:abstractNumId w:val="802057"/></w:num><w:num w:numId="15"><w:abstractNumId w:val="802058"/></w:num><w:num w:numId="16"><w:abstractNumId w:val="802059"/></w:num><w:num w:numId="17"><w:abstractNumId w:val="802060"/></w:num><w:num w:numId="18"><w:abstractNumId w:val="802061"/></w:num><w:num w:numId="19"><w:abstractNumId w:val="802062"/></w:num><w:num w:numId="20"><w:abstractNumId w:val="802063"/></w:num><w:num w:numId="21"><w:abstractNumId w:val="802064"/></w:num><w:num w:numId="22"><w:abstractNumId w:val="802065"/></w:num><w:num w:numId="23"><w:abstractNumId w:val="802066"/></w:num><w:num w:numId="24"><w:abstractNumId w:val="802067"/></w:num><w:num w:numId="25"><w:abstractNumId w:val="802068"/></w:num><w:num w:numId="26"><w:abstractNumId w:val="802069"/></w:num><w:num w:numId="27"><w:abstractNumId w:val="802070"/></w:num><w:num w:numId="28"><w:abstractNumId w:val="802071"/></w:num><w:num w:numId="29"><w:abstractNumId w:val="802072"/></w:num><w:num w:numId="30"><w:abstractNumId w:val="802073"/></w:num><w:num w:numId="31"><w:abstractNumId w:val="802074"/></w:num><w:num w:numId="32"><w:abstractNumId w:val="802075"/></w:num><w:num w:numId="33"><w:abstractNumId w:val="802076"/></w:num><w:num w:numId="34"><w:abstractNumId w:val="802077"/></w:num><w:num w:numId="35"><w:abstractNumId w:val="802078"/></w:num><w:num w:numId="36"><w:abstractNumId w:val="802079"/></w:num><w:num w:numId="37"><w:abstractNumId w:val="802080"/></w:num><w:num w:numId="38"><w:abstractNumId w:val="802081"/></w:num><w:num w:numId="39"><w:abstractNumId w:val="802082"/></w:num><w:num w:numId="40"><w:abstractNumId w:val="802083"/></w:num><w:num w:numId="41"><w:abstractNumId w:val="802084"/></w:num><w:num w:numId="42"><w:abstractNumId w:val="802085"/></w:num><w:num w:numId="43"><w:abstractNumId w:val="802086"/></w:num><w:num w:numId="44"><w:abstractNumId w:val="802087"/></w:num><w:num w:numId="45"><w:abstractNumId w:val="802088"/></w:num><w:num w:numId="46"><w:abstractNumId w:val="802089"/></w:num><w:num w:numId="47"><w:abstractNumId w:val="802090"/></w:num><w:num w:numId="48"><w:abstractNumId w:val="802091"/></w:num><w:num w:numId="49"><w:abstractNumId w:val="802092"/></w:num><w:num w:numId="50"><w:abstractNumId w:val="802093"/></w:num><w:num w:numId="51"><w:abstractNumId w:val="802094"/></w:num><w:num w:numId="52"><w:abstractNumId w:val="802095"/></w:num><w:num w:numId="53"><w:abstractNumId w:val="802096"/></w:num></w:numbering>